<?xml version="1.0" encoding="UTF-8"?>
<beans xmlns="http://www.springframework.org/schema/beans"
	xmlns:xsi="http://www.w3.org/2001/XMLSchema-instance"
	xmlns:util="http://www.springframework.org/schema/util"
	xsi:schemaLocation="http://www.springframework.org/schema/beans http://www.springframework.org/schema/beans/spring-beans.xsd http://www.springframework.org/schema/util http://www.springframework.org/schema/util/spring-util-2.5.xsd">

	<!--+
	    | analyzer (==tokenizer/normalizer)
	    +-->
    <bean id="luceneFieldAnalyzerMap" class="org.springframework.beans.factory.config.MapFactoryBean">
  		<property name="sourceMap">
  			<map>
  				<entry key="author" value-ref="luceneStandardAnalyzer"/>
  				<entry key="user_name" value-ref="luceneStandardAnalyzer"/>
  				<entry key="mergedfields" value-ref="luceneGermanAnalyzer"/>
  			</map>
  		</property>
  	</bean>

	<bean id="luceneStandardAnalyzer" class="org.apache.lucene.analysis.standard.StandardAnalyzer"/>
	
	<bean id="luceneGermanAnalyzer" class="org.apache.lucene.analysis.de.GermanAnalyzer"/>
	
	<bean id="luceneFieldWrapperAnalyzer" class="org.bibsonomy.lucene.index.analyzer.SpringPerFieldAnalyzerWrapper" factory-method="getPreInitInstance">
		<property name="defaultAnalyzer" ref="luceneStandardAnalyzer"/>
		<property name="fieldMap" ref="luceneFieldAnalyzerMap"/>
	</bean>

</beans>
